threadingbatch/LICENSE
threadingbatch/README.MD
threadingbatch/__init__.py
threadingbatch/requirements.txt
threadingbatch/thirdparty.json
threadingbatch-0.10.dist-info/LICENSE.rst
threadingbatch-0.10.dist-info/METADATA
threadingbatch-0.10.dist-info/WHEEL
threadingbatch-0.10.dist-info/top_level.txt
threadingbatch-0.10.dist-info/RECORD
